[
  {
    "name": "Layout",
    "comment": " [Bulma layout](http://bulma.io/documentation/layout/container/)\n\n@docs container, footer, hero, section\n\n",
    "aliases": [],
    "types": [],
    "values": [
      {
        "name": "container",
        "comment": " [`<div class=\"container\">`](http://bulma.io/documentation/layout/container/)\n",
        "type": "List (Html.Attribute msg) -> List (Html.Html msg) -> Html.Html msg"
      },
      {
        "name": "footer",
        "comment": " [`<footer class=\"footer\">`](http://bulma.io/documentation/layout/footer/)\n",
        "type": "List (Html.Attribute msg) -> List (Html.Html msg) -> Html.Html msg"
      },
      {
        "name": "hero",
        "comment": " [`<section class=\"hero\">`](http://bulma.io/documentation/layout/hero/)\n",
        "type": "List (Html.Attribute msg) -> List (Html.Html msg) -> Html.Html msg"
      },
      {
        "name": "section",
        "comment": " [`<section class=\"section\">`](http://bulma.io/documentation/layout/section/)\n",
        "type": "List (Html.Attribute msg) -> List (Html.Html msg) -> Html.Html msg"
      }
    ],
    "generated-with-elm-version": "0.18.0"
  },
  {
    "name": "Form",
    "comment": " [Bulma form](http://bulma.io/documentation/form/general/)\n\n@docs field, button, control, fieldBody, fieldLabel, input, label, select, textarea\n\n",
    "aliases": [],
    "types": [],
    "values": [
      {
        "name": "button",
        "comment": " [`<button class=\"button\">`](http://bulma.io/documentation/form/general/)\n",
        "type": "List (Html.Attribute msg) -> List (Html.Html msg) -> Html.Html msg"
      },
      {
        "name": "control",
        "comment": " [`<p class=\"control\">`](http://bulma.io/documentation/form/general/)\n",
        "type": "List (Html.Attribute msg) -> List (Html.Html msg) -> Html.Html msg"
      },
      {
        "name": "field",
        "comment": " [`<div class=\"field\">`](http://bulma.io/documentation/form/general/)\n",
        "type": "List (Html.Attribute msg) -> List (Html.Html msg) -> Html.Html msg"
      },
      {
        "name": "fieldBody",
        "comment": " [`<div class=\"field-body\">`](http://bulma.io/documentation/form/general/)\n",
        "type": "List (Html.Attribute msg) -> List (Html.Html msg) -> Html.Html msg"
      },
      {
        "name": "fieldLabel",
        "comment": " [`<div class=\"field-label\" attributes...>str</div>`](http://bulma.io/documentation/form/general/)\n",
        "type": "List (Html.Attribute msg) -> String -> Html.Html msg"
      },
      {
        "name": "input",
        "comment": " [`<input class=\"input\">`](http://bulma.io/documentation/form/input/)\n",
        "type": "List (Html.Attribute msg) -> Html.Html msg"
      },
      {
        "name": "label",
        "comment": " [`<label class=\"label\">str</label>`](http://bulma.io/documentation/form/general/)\n",
        "type": "String -> Html.Html msg"
      },
      {
        "name": "select",
        "comment": " [`<div class=\"select\">`](http://bulma.io/documentation/form/select/)\n",
        "type": "List (Html.Attribute msg) -> List (Html.Html msg) -> Html.Html msg"
      },
      {
        "name": "textarea",
        "comment": " [`<textarea class=\"textarea\">`](http://bulma.io/documentation/form/textarea/)\n",
        "type": "List (Html.Attribute msg) -> List (Html.Html msg) -> Html.Html msg"
      }
    ],
    "generated-with-elm-version": "0.18.0"
  },
  {
    "name": "Components.Tabs",
    "comment": " [Bulma tabs component](http://bulma.io/documentation/components/tabs/)\n\n@docs root\n\n",
    "aliases": [],
    "types": [],
    "values": [
      {
        "name": "root",
        "comment": " [`<div class=\"tabs\">`](http://bulma.io/documentation/components/tabs/)\n",
        "type": "List (Html.Attribute msg) -> List (Html.Html msg) -> Html.Html msg"
      }
    ],
    "generated-with-elm-version": "0.18.0"
  },
  {
    "name": "Components.Navbar",
    "comment": " [Bulma navbar component](http://bulma.io/documentation/components/navbar/)\n\n@docs root, aItem, aLink, brand, burger, divItem, divLink, dropdown, menu, menuEnd, menuStart\n\n",
    "aliases": [],
    "types": [],
    "values": [
      {
        "name": "aItem",
        "comment": " [`<a class=\"navbar-item\">`](http://bulma.io/documentation/components/navbar/)\n",
        "type": "List (Html.Attribute msg) -> List (Html.Html msg) -> Html.Html msg"
      },
      {
        "name": "aLink",
        "comment": " [`<a class=\"navbar-link\">`](http://bulma.io/documentation/components/navbar/)\n",
        "type": "List (Html.Attribute msg) -> List (Html.Html msg) -> Html.Html msg"
      },
      {
        "name": "brand",
        "comment": " [`<div class=\"navbar-brand\">`](http://bulma.io/documentation/components/navbar/)\n",
        "type": "List (Html.Attribute msg) -> List (Html.Html msg) -> Html.Html msg"
      },
      {
        "name": "burger",
        "comment": " [`<div class=\"navbar-burger\">`](http://bulma.io/documentation/components/navbar/)\n",
        "type": "List (Html.Attribute msg) -> List (Html.Html msg) -> Html.Html msg"
      },
      {
        "name": "divItem",
        "comment": " [`<div class=\"navbar-item\">`](http://bulma.io/documentation/components/navbar/)\n",
        "type": "List (Html.Attribute msg) -> List (Html.Html msg) -> Html.Html msg"
      },
      {
        "name": "divLink",
        "comment": " [`<div class=\"navbar-link\">`](http://bulma.io/documentation/components/navbar/)\n",
        "type": "List (Html.Attribute msg) -> List (Html.Html msg) -> Html.Html msg"
      },
      {
        "name": "dropdown",
        "comment": " [`<div class=\"navbar-dropdown\">`](http://bulma.io/documentation/components/navbar/)\n",
        "type": "List (Html.Attribute msg) -> List (Html.Html msg) -> Html.Html msg"
      },
      {
        "name": "menu",
        "comment": " [`<div class=\"navbar-menu\">`](http://bulma.io/documentation/components/navbar/)\n",
        "type": "List (Html.Attribute msg) -> List (Html.Html msg) -> Html.Html msg"
      },
      {
        "name": "menuEnd",
        "comment": " [`<div class=\"navbar-end\">`](http://bulma.io/documentation/components/navbar/)\n",
        "type": "List (Html.Attribute msg) -> List (Html.Html msg) -> Html.Html msg"
      },
      {
        "name": "menuStart",
        "comment": " [`<div class=\"navbar-start\">`](http://bulma.io/documentation/components/navbar/)\n",
        "type": "List (Html.Attribute msg) -> List (Html.Html msg) -> Html.Html msg"
      },
      {
        "name": "root",
        "comment": " [`<nav class=\"navbar\">`](http://bulma.io/documentation/components/navbar/)\n",
        "type": "List (Html.Attribute msg) -> List (Html.Html msg) -> Html.Html msg"
      }
    ],
    "generated-with-elm-version": "0.18.0"
  },
  {
    "name": "Components.Level",
    "comment": " [Bulma level component](http://bulma.io/documentation/components/level/)\n\n@docs root, aItem, divItem, left, pItem, right\n\n",
    "aliases": [],
    "types": [],
    "values": [
      {
        "name": "aItem",
        "comment": " [`<a class=\"level-item\">`](http://bulma.io/documentation/components/level/)\n",
        "type": "List (Html.Attribute msg) -> List (Html.Html msg) -> Html.Html msg"
      },
      {
        "name": "divItem",
        "comment": " [`<div class=\"level-item\">`](http://bulma.io/documentation/components/level/)\n",
        "type": "List (Html.Attribute msg) -> List (Html.Html msg) -> Html.Html msg"
      },
      {
        "name": "left",
        "comment": " [`<div class=\"level-left\">`](http://bulma.io/documentation/components/level/)\n",
        "type": "List (Html.Attribute msg) -> List (Html.Html msg) -> Html.Html msg"
      },
      {
        "name": "pItem",
        "comment": " [`<p class=\"level-item\">`](http://bulma.io/documentation/components/level/)\n",
        "type": "List (Html.Attribute msg) -> List (Html.Html msg) -> Html.Html msg"
      },
      {
        "name": "right",
        "comment": " [`<div class=\"level-right\">`](http://bulma.io/documentation/components/level/)\n",
        "type": "List (Html.Attribute msg) -> List (Html.Html msg) -> Html.Html msg"
      },
      {
        "name": "root",
        "comment": " [`<nav class=\"level\">`](http://bulma.io/documentation/components/level/)\n",
        "type": "List (Html.Attribute msg) -> List (Html.Html msg) -> Html.Html msg"
      }
    ],
    "generated-with-elm-version": "0.18.0"
  },
  {
    "name": "Components.Message",
    "comment": " [Bulma message component](http://bulma.io/documentation/components/message/)\n\n@docs root, body, header\n\n",
    "aliases": [],
    "types": [],
    "values": [
      {
        "name": "body",
        "comment": " [`<div class=\"message-body\">`](http://bulma.io/documentation/components/message/)\n",
        "type": "List (Html.Attribute msg) -> List (Html.Html msg) -> Html.Html msg"
      },
      {
        "name": "header",
        "comment": " [`<article class=\"message-header\">`](http://bulma.io/documentation/components/message/)\n",
        "type": "List (Html.Attribute msg) -> List (Html.Html msg) -> Html.Html msg"
      },
      {
        "name": "root",
        "comment": " [`<article class=\"message\">`](http://bulma.io/documentation/components/message/)\n",
        "type": "List (Html.Attribute msg) -> List (Html.Html msg) -> Html.Html msg"
      }
    ],
    "generated-with-elm-version": "0.18.0"
  },
  {
    "name": "Components.Panel",
    "comment": " [Bulma panel component](http://bulma.io/documentation/components/panel/)\n\n@docs root, aBlock, divBlock, heading, icon, labelBlock, tabs\n\n",
    "aliases": [],
    "types": [],
    "values": [
      {
        "name": "aBlock",
        "comment": " [`<a class=\"panel-block\">`](http://bulma.io/documentation/components/panel/)\n",
        "type": "List (Html.Attribute msg) -> List (Html.Html msg) -> Html.Html msg"
      },
      {
        "name": "divBlock",
        "comment": " [`<div class=\"panel-block\">`](http://bulma.io/documentation/components/panel/)\n",
        "type": "List (Html.Attribute msg) -> List (Html.Html msg) -> Html.Html msg"
      },
      {
        "name": "heading",
        "comment": " [`<p class=\"panel-heading\">`](http://bulma.io/documentation/components/panel/)\n",
        "type": "List (Html.Attribute msg) -> List (Html.Html msg) -> Html.Html msg"
      },
      {
        "name": "icon",
        "comment": " [`<span class=\"panel-icon\">`](http://bulma.io/documentation/components/panel/)\n",
        "type": "List (Html.Attribute msg) -> List (Html.Html msg) -> Html.Html msg"
      },
      {
        "name": "labelBlock",
        "comment": " [`<label class=\"panel-block\">`](http://bulma.io/documentation/components/panel/)\n",
        "type": "List (Html.Attribute msg) -> List (Html.Html msg) -> Html.Html msg"
      },
      {
        "name": "root",
        "comment": " [`<nav class=\"panel\">`](http://bulma.io/documentation/components/panel/)\n",
        "type": "List (Html.Attribute msg) -> List (Html.Html msg) -> Html.Html msg"
      },
      {
        "name": "tabs",
        "comment": " [`<p class=\"panel-tabs\">`](http://bulma.io/documentation/components/panel/)\n",
        "type": "List (Html.Attribute msg) -> List (Html.Html msg) -> Html.Html msg"
      }
    ],
    "generated-with-elm-version": "0.18.0"
  },
  {
    "name": "Elements",
    "comment": " [Bulma elements](http://bulma.io/documentation/elements/box/)\n\n@docs box, button, content, delete, deleteButton, icon, notification, subtitle, table, tag, title\n\n",
    "aliases": [],
    "types": [],
    "values": [
      {
        "name": "box",
        "comment": " [`<div class=\"box\">`](http://bulma.io/documentation/elements/box/)\n",
        "type": "List (Html.Attribute msg) -> List (Html.Html msg) -> Html.Html msg"
      },
      {
        "name": "button",
        "comment": " [`<a class=\"button\">`](http://bulma.io/documentation/elements/button/)\n",
        "type": "List (Html.Attribute msg) -> List (Html.Html msg) -> Html.Html msg"
      },
      {
        "name": "content",
        "comment": " [`<div class=\"content\">`](http://bulma.io/documentation/elements/content/)\n",
        "type": "List (Html.Attribute msg) -> List (Html.Html msg) -> Html.Html msg"
      },
      {
        "name": "delete",
        "comment": " [`<a class=\"delete\">`](http://bulma.io/documentation/elements/delete/)\n",
        "type": "List (Html.Attribute msg) -> Html.Html msg"
      },
      {
        "name": "deleteButton",
        "comment": " [`<button class=\"delete\">`](http://bulma.io/documentation/elements/delete/)\n",
        "type": "List (Html.Attribute msg) -> Html.Html msg"
      },
      {
        "name": "icon",
        "comment": " [`<span class=\"icon\" attributes...><i class=\"fa fa-icon\"></i></span>`](http://bulma.io/documentation/elements/icon/)\n",
        "type": "List (Html.Attribute msg) -> String -> Html.Html msg"
      },
      {
        "name": "notification",
        "comment": " [`<div class=\"notification\">`](http://bulma.io/documentation/elements/notification/)\n",
        "type": "List (Html.Attribute msg) -> List (Html.Html msg) -> Html.Html msg"
      },
      {
        "name": "subtitle",
        "comment": " [`<h{size} class=\"subtitle is-{size}>{txt}</h{size}>\"`](http://bulma.io/documentation/elements/title/)\n",
        "type": "Int -> String -> Html.Html msg"
      },
      {
        "name": "table",
        "comment": " [`<table class=\"table\">`](http://bulma.io/documentation/elements/table/)\n",
        "type": "List (Html.Attribute msg) -> List (Html.Html msg) -> Html.Html msg"
      },
      {
        "name": "tag",
        "comment": " [`<span class=\"tag\">`](http://bulma.io/documentation/elements/tag/)\n",
        "type": "List (Html.Attribute msg) -> List (Html.Html msg) -> Html.Html msg"
      },
      {
        "name": "title",
        "comment": " [`<h{size} class=\"title is-{size}>{txt}</h{size}>\"`](http://bulma.io/documentation/elements/title/)\n",
        "type": "Int -> String -> Html.Html msg"
      }
    ],
    "generated-with-elm-version": "0.18.0"
  },
  {
    "name": "Components.Modal",
    "comment": " [Bulma modal component](http://bulma.io/documentation/components/modal/)\n\n@docs root, background, card, cardBody, cardFoot, cardHead, cardTitle, close, content\n\n",
    "aliases": [],
    "types": [],
    "values": [
      {
        "name": "background",
        "comment": " [`<div class=\"modal-background\">`](http://bulma.io/documentation/components/modal/)\n",
        "type": "List (Html.Attribute msg) -> List (Html.Html msg) -> Html.Html msg"
      },
      {
        "name": "card",
        "comment": " [`<div class=\"modal-card\">`](http://bulma.io/documentation/components/modal/)\n",
        "type": "List (Html.Attribute msg) -> List (Html.Html msg) -> Html.Html msg"
      },
      {
        "name": "cardBody",
        "comment": " [`<section class=\"modal-card-body\">`](http://bulma.io/documentation/components/modal/)\n",
        "type": "List (Html.Attribute msg) -> List (Html.Html msg) -> Html.Html msg"
      },
      {
        "name": "cardFoot",
        "comment": " [`<footer class=\"modal-card-foot\">`](http://bulma.io/documentation/components/modal/)\n",
        "type": "List (Html.Attribute msg) -> List (Html.Html msg) -> Html.Html msg"
      },
      {
        "name": "cardHead",
        "comment": " [`<header class=\"modal-card-head\">`](http://bulma.io/documentation/components/modal/)\n",
        "type": "List (Html.Attribute msg) -> List (Html.Html msg) -> Html.Html msg"
      },
      {
        "name": "cardTitle",
        "comment": " [`<p class=\"modal-card-title\">`](http://bulma.io/documentation/components/modal/)\n",
        "type": "List (Html.Attribute msg) -> List (Html.Html msg) -> Html.Html msg"
      },
      {
        "name": "close",
        "comment": " [`<button class=\"modal-close\">`](http://bulma.io/documentation/components/modal/)\n",
        "type": "List (Html.Attribute msg) -> List (Html.Html msg) -> Html.Html msg"
      },
      {
        "name": "content",
        "comment": " [`<div class=\"modal-content\">`](http://bulma.io/documentation/components/modal/)\n",
        "type": "List (Html.Attribute msg) -> List (Html.Html msg) -> Html.Html msg"
      },
      {
        "name": "root",
        "comment": " [`<div class=\"modal\">`](http://bulma.io/documentation/components/modal/)\n",
        "type": "List (Html.Attribute msg) -> List (Html.Html msg) -> Html.Html msg"
      }
    ],
    "generated-with-elm-version": "0.18.0"
  },
  {
    "name": "Components.Media",
    "comment": " [Bulma media component](http://bulma.io/documentation/components/media-object/)\n\n@docs root, content, left, right\n\n",
    "aliases": [],
    "types": [],
    "values": [
      {
        "name": "content",
        "comment": " [`<div class=\"media-content\">`](http://bulma.io/documentation/components/media-object/)\n",
        "type": "List (Html.Attribute msg) -> List (Html.Html msg) -> Html.Html msg"
      },
      {
        "name": "left",
        "comment": " [`<figure class=\"media-left\">`](http://bulma.io/documentation/components/media-object/)\n",
        "type": "List (Html.Attribute msg) -> List (Html.Html msg) -> Html.Html msg"
      },
      {
        "name": "right",
        "comment": " [`<div class=\"media-right\">`](http://bulma.io/documentation/components/media-object/)\n",
        "type": "List (Html.Attribute msg) -> List (Html.Html msg) -> Html.Html msg"
      },
      {
        "name": "root",
        "comment": " [`<article class=\"media\">`](http://bulma.io/documentation/components/media-object/)\n",
        "type": "List (Html.Attribute msg) -> List (Html.Html msg) -> Html.Html msg"
      }
    ],
    "generated-with-elm-version": "0.18.0"
  },
  {
    "name": "Components.Dropdown",
    "comment": " [Bulma dropdown component](http://bulma.io/documentation/components/dropdown/)\n\n@docs root, aItem, content, divItem, divider, menu, trigger\n\n",
    "aliases": [],
    "types": [],
    "values": [
      {
        "name": "aItem",
        "comment": " [`<a class=\"dropdown-item\">`](http://bulma.io/documentation/components/dropdown/)\n",
        "type": "List (Html.Attribute msg) -> List (Html.Html msg) -> Html.Html msg"
      },
      {
        "name": "content",
        "comment": " [`<a class=\"dropdown-content\">`](http://bulma.io/documentation/components/dropdown/)\n",
        "type": "List (Html.Attribute msg) -> List (Html.Html msg) -> Html.Html msg"
      },
      {
        "name": "divItem",
        "comment": " [`<div class=\"dropdown-item\">`](http://bulma.io/documentation/components/dropdown/)\n",
        "type": "List (Html.Attribute msg) -> List (Html.Html msg) -> Html.Html msg"
      },
      {
        "name": "divider",
        "comment": " [`<hr class=\"dropdown-divider\">`](http://bulma.io/documentation/components/dropdown/)\n",
        "type": "Html.Html msg"
      },
      {
        "name": "menu",
        "comment": " [`<div class=\"dropdown-menu\">`](http://bulma.io/documentation/components/dropdown/)\n",
        "type": "List (Html.Attribute msg) -> List (Html.Html msg) -> Html.Html msg"
      },
      {
        "name": "root",
        "comment": " [`<div class=\"dropdown\">`](http://bulma.io/documentation/components/dropdown/)\n",
        "type": "List (Html.Attribute msg) -> List (Html.Html msg) -> Html.Html msg"
      },
      {
        "name": "trigger",
        "comment": " [`<div class=\"dropdown-trigger\">`](http://bulma.io/documentation/components/dropdown/)\n",
        "type": "List (Html.Attribute msg) -> List (Html.Html msg) -> Html.Html msg"
      }
    ],
    "generated-with-elm-version": "0.18.0"
  },
  {
    "name": "Columns",
    "comment": " [Bulma columns](http://bulma.io/documentation/columns/basics/)\n\n@docs column, columns\n\n",
    "aliases": [],
    "types": [],
    "values": [
      {
        "name": "column",
        "comment": " [`<div class=\"column\">`](http://bulma.io/documentation/columns/basics/)\n",
        "type": "List (Html.Attribute msg) -> List (Html.Html msg) -> Html.Html msg"
      },
      {
        "name": "columns",
        "comment": " [`<div class=\"columns\">`](http://bulma.io/documentation/columns/basics/)\n",
        "type": "List (Html.Attribute msg) -> List (Html.Html msg) -> Html.Html msg"
      }
    ],
    "generated-with-elm-version": "0.18.0"
  }
]