[
  {
    "name": "Octicons",
    "comment": " @docs\n# Configuration\n@docs size, style, width, height, fillRule, margin, color\n\n# Icons Helpers\n@docs alert, arrowDown, arrowLeft, arrowRight,arrowSmallDown\n@docs arrowSmallLeft, arrowSmallRight\n@docs arrowSmallUp, arrowUp, beaker, bell, bold\n@docs book, bookmark, briefcase, broadcast, browser, bug, calendar\n@docs check, checklist, chevronDown, chevronLeft, chevronRight\n@docs chevronUp, circleSlash, circuitBoard, clippy, clock\n@docs cloudDownload, cloudUpload, code, comment, commentDiscussion\n@docs creditCard, dash, dashboard, database, desktopDownload, deviceCamera\n@docs deviceCameraVideo, deviceDesktop, deviceMobile\n@docs diff, diffAdded, diffIgnored, diffModified\n@docs diffRemoved diffRenamed, ellipses, ellipsis, eye, file\n@docs fileBinary, fileCode, fileDirectory, fileMedia, filePdf\n@docs fileSubmodule, fileSymlinkDirectory, fileSymlinkFile, fileText, fileZip\n@docs flame, fold, gear, gift, gist, gistSecret, gitBranch, gitCommit\n@docs gitCompare, gitMerge, gitPullRequest, globe, grabber, graph, heart\n@docs history, home, horizontalRule, hubot, inbox, info, issueClosed, issueOpened\n@docs issueReopened, italic, jersey, key, keyboard, law, lightBulb\n@docs link, linkExternal, listOrdered, listUnordered, location, lock\n@docs logoGist, logoGithub, mail, mailRead, mailReply, markGithub, markTor, markTwitter\n@docs markdown, megaphone, mention, milestone, mirror, mortarBoard\n@docs mute, noNewline, note, octoface\n@docs organization, package, paintcan, pencil, person, pin, plug, plus\n@docs plusSmall, primitiveDot, primitiveSquare\n@docs project, pulse, question, quote, radioTower, reply, repo\n@docs repoClone, repoForcePush, repoForked, repoPull, repoPush, rocket, rss\n@docs ruby, screenFull, screenNormal, search, server, settings, shield, signIn\n@docs signOut, smiley, squirrel, star, stop, sync, tag, tasklist, telescope\n@docs terminal, textSize, threeBars, thumbsdown, thumbsup, tools\n@docs trashcan, triangleDown, triangleLeft, triangleRight, triangleUp\n@docs unfold, unmute, unverified, verified, versions, watch, x\n@docs zap\n\n# Custom Octicons\n\n@docs pathIconWithOptions, polygonIconWithOptions, Options, defaultOptions\n\n# Svg Data\n@docs alertPath, arrowDownPolygon, arrowLeftPolygon, arrowRightPolygon, arrowSmallDownPolygon\n@docs arrowSmallLeftPolygon, arrowSmallRightPolygon, arrowSmallUpPolygon, arrowUpPolygon\n@docs beakerPath, bellPath, boldPath, bookPath, bookmarkPath, briefcasePath, broadcastPath\n@docs browserPath, bugPath, calendarPath, checkPolygon, checklistPath, chevronDownPolygon\n@docs chevronLeftPolygon, chevronRightPolygon, chevronUpPolygon, circleSlashPath\n@docs circuitBoardPath, clippyPath, clockPath, cloudDownloadPath, cloudUploadPath, codePath\n@docs commentDiscussionPath, commentPath, creditCardPath, dashPolygon, dashboardPath\n@docs databasePath, desktopDownloadPath, deviceCameraPath, deviceCameraVideoPath\n@docs deviceDesktopPath, deviceMobilePath, diffAddedPath, diffIgnoredPath\n@docs diffModifiedPath, diffPath, diffRemovedPath, diffRenamed, diffRenamedPath, ellipses\n@docs ellipsesPath, ellipsis, ellipsisPath, eye, eyePath, file, fileBinaryPath, fileCodePath\n@docs fileDirectoryPath, fileMediaPath, filePath, filePdfPath, fileSubmodulePath\n@docs fileSymlinkDirectoryPath, fileSymlinkFilePath, fileTextPath, fileZipPath, flamePath\n@docs foldPath, gearPath, giftPath, gistPath, gistSecretPath, gitBranchPath, gitCommitPath\n@docs gitComparePath, gitMergePath, gitPullRequestPath, globePath, grabberPath, graphPath\n@docs heartPath, historyPath, homePath, horizontalRulePath, hubotPath, inboxPath, infoPath\n@docs issueClosedPath, issueOpenedPath, issueReopenedPath, italicPath, jerseyPath, keyPath\n@docs keyboardPath, lawPath, lightBulbPath, linkExternalPath, linkPath, listOrderedPath\n@docs listUnorderedPath, locationPath, lockPath, logoGistPath, logoGithubPath, mailPath\n@docs mailReadPath, mailReplyPath, markGithubPath, markTorPath, markTwitterPath, markdownPath, megaphonePath, mentionPath\n@docs milestonePath, mirrorPath, mortarBoardPath, mutePath, noNewlinePath, notePath\n@docs octofacePath, organizationPath, packagePath, paintcanPath, pencilPath, personPath\n@docs pinPath, plugPath, plusPolygon, plusSmallPath, primitiveDotPath\n@docs primitiveSquarePolygon, projectPath, pulsePolygon, questionPath, quotePath\n@docs radioTowerPath, replyPath, repoClonePath, repoForcePushPath, repoForkedPath, repoPath\n@docs repoPullPath, repoPushPath, rocketPath, rssPath, rubyPath, screenFullPath\n@docs screenNormalPath, searchPath, serverPath, settingsPath, shieldPath, signInPath\n@docs signOutPath, smileyPath, squirrelPath, starPolygon, stopPath, syncPath, tagPath\n@docs tasklistPath, telescopePath, terminalPath, textSizePath, threeBarsPath\n@docs thumbsdownPath, thumbsupPath, toolsPath, trashcanPath, triangleDownPolygon\n@docs triangleLeftPolygon, triangleRightPolygon, triangleUpPolygon, unfoldPath, unmutePath\n@docs unverifiedPath, verifiedPath, versionsPath, watchPath, xPolygon, zapPolygon\n",
    "aliases": [
      {
        "name": "Options",
        "comment": "\n",
        "args": [],
        "type": "Octicons.Internal.Options"
      }
    ],
    "types": [],
    "values": [
      {
        "name": "alert",
        "comment": "\n",
        "type": "Octicons.Options -> Html.Html msg"
      },
      {
        "name": "alertPath",
        "comment": "\n",
        "type": "String"
      },
      {
        "name": "arrowDown",
        "comment": "\n",
        "type": "Octicons.Options -> Html.Html msg"
      },
      {
        "name": "arrowDownPolygon",
        "comment": "\n",
        "type": "String"
      },
      {
        "name": "arrowLeft",
        "comment": "\n",
        "type": "Octicons.Options -> Html.Html msg"
      },
      {
        "name": "arrowLeftPolygon",
        "comment": "\n",
        "type": "String"
      },
      {
        "name": "arrowRight",
        "comment": "\n",
        "type": "Octicons.Options -> Html.Html msg"
      },
      {
        "name": "arrowRightPolygon",
        "comment": "\n",
        "type": "String"
      },
      {
        "name": "arrowSmallDown",
        "comment": "\n",
        "type": "Octicons.Options -> Html.Html msg"
      },
      {
        "name": "arrowSmallDownPolygon",
        "comment": "\n",
        "type": "String"
      },
      {
        "name": "arrowSmallLeft",
        "comment": "\n",
        "type": "Octicons.Options -> Html.Html msg"
      },
      {
        "name": "arrowSmallLeftPolygon",
        "comment": "\n",
        "type": "String"
      },
      {
        "name": "arrowSmallRight",
        "comment": "\n",
        "type": "Octicons.Options -> Html.Html msg"
      },
      {
        "name": "arrowSmallRightPolygon",
        "comment": "\n",
        "type": "String"
      },
      {
        "name": "arrowSmallUp",
        "comment": "\n",
        "type": "Octicons.Options -> Html.Html msg"
      },
      {
        "name": "arrowSmallUpPolygon",
        "comment": "\n",
        "type": "String"
      },
      {
        "name": "arrowUp",
        "comment": "\n",
        "type": "Octicons.Options -> Html.Html msg"
      },
      {
        "name": "arrowUpPolygon",
        "comment": "\n",
        "type": "String"
      },
      {
        "name": "beaker",
        "comment": "\n",
        "type": "Octicons.Options -> Html.Html msg"
      },
      {
        "name": "beakerPath",
        "comment": "\n",
        "type": "String"
      },
      {
        "name": "bell",
        "comment": "\n",
        "type": "Octicons.Options -> Html.Html msg"
      },
      {
        "name": "bellPath",
        "comment": "\n",
        "type": "String"
      },
      {
        "name": "bold",
        "comment": "\n",
        "type": "Octicons.Options -> Html.Html msg"
      },
      {
        "name": "boldPath",
        "comment": "\n",
        "type": "String"
      },
      {
        "name": "book",
        "comment": "\n",
        "type": "Octicons.Options -> Html.Html msg"
      },
      {
        "name": "bookPath",
        "comment": "\n",
        "type": "String"
      },
      {
        "name": "bookmark",
        "comment": "\n",
        "type": "Octicons.Options -> Html.Html msg"
      },
      {
        "name": "bookmarkPath",
        "comment": "\n",
        "type": "String"
      },
      {
        "name": "briefcase",
        "comment": "\n",
        "type": "Octicons.Options -> Html.Html msg"
      },
      {
        "name": "briefcasePath",
        "comment": "\n",
        "type": "String"
      },
      {
        "name": "broadcast",
        "comment": "\n",
        "type": "Octicons.Options -> Html.Html msg"
      },
      {
        "name": "broadcastPath",
        "comment": "\n",
        "type": "String"
      },
      {
        "name": "browser",
        "comment": "\n",
        "type": "Octicons.Options -> Html.Html msg"
      },
      {
        "name": "browserPath",
        "comment": "\n",
        "type": "String"
      },
      {
        "name": "bug",
        "comment": "\n",
        "type": "Octicons.Options -> Html.Html msg"
      },
      {
        "name": "bugPath",
        "comment": "\n",
        "type": "String"
      },
      {
        "name": "calendar",
        "comment": "\n",
        "type": "Octicons.Options -> Html.Html msg"
      },
      {
        "name": "calendarPath",
        "comment": "\n",
        "type": "String"
      },
      {
        "name": "check",
        "comment": "\n",
        "type": "Octicons.Options -> Html.Html msg"
      },
      {
        "name": "checkPolygon",
        "comment": "\n",
        "type": "String"
      },
      {
        "name": "checklist",
        "comment": "\n",
        "type": "Octicons.Options -> Html.Html msg"
      },
      {
        "name": "checklistPath",
        "comment": "\n",
        "type": "String"
      },
      {
        "name": "chevronDown",
        "comment": "\n",
        "type": "Octicons.Options -> Html.Html msg"
      },
      {
        "name": "chevronDownPolygon",
        "comment": "\n",
        "type": "String"
      },
      {
        "name": "chevronLeft",
        "comment": "\n",
        "type": "Octicons.Options -> Html.Html msg"
      },
      {
        "name": "chevronLeftPolygon",
        "comment": "\n",
        "type": "String"
      },
      {
        "name": "chevronRight",
        "comment": "\n",
        "type": "Octicons.Options -> Html.Html msg"
      },
      {
        "name": "chevronRightPolygon",
        "comment": "\n",
        "type": "String"
      },
      {
        "name": "chevronUp",
        "comment": "\n",
        "type": "Octicons.Options -> Html.Html msg"
      },
      {
        "name": "chevronUpPolygon",
        "comment": "\n",
        "type": "String"
      },
      {
        "name": "circleSlash",
        "comment": "\n",
        "type": "Octicons.Options -> Html.Html msg"
      },
      {
        "name": "circleSlashPath",
        "comment": "\n",
        "type": "String"
      },
      {
        "name": "circuitBoard",
        "comment": "\n",
        "type": "Octicons.Options -> Html.Html msg"
      },
      {
        "name": "circuitBoardPath",
        "comment": "\n",
        "type": "String"
      },
      {
        "name": "clippy",
        "comment": "\n",
        "type": "Octicons.Options -> Html.Html msg"
      },
      {
        "name": "clippyPath",
        "comment": "\n",
        "type": "String"
      },
      {
        "name": "clock",
        "comment": "\n",
        "type": "Octicons.Options -> Html.Html msg"
      },
      {
        "name": "clockPath",
        "comment": "\n",
        "type": "String"
      },
      {
        "name": "cloudDownload",
        "comment": "\n",
        "type": "Octicons.Options -> Html.Html msg"
      },
      {
        "name": "cloudDownloadPath",
        "comment": "\n",
        "type": "String"
      },
      {
        "name": "cloudUpload",
        "comment": "\n",
        "type": "Octicons.Options -> Html.Html msg"
      },
      {
        "name": "cloudUploadPath",
        "comment": "\n",
        "type": "String"
      },
      {
        "name": "code",
        "comment": "\n",
        "type": "Octicons.Options -> Html.Html msg"
      },
      {
        "name": "codePath",
        "comment": "\n",
        "type": "String"
      },
      {
        "name": "color",
        "comment": "\n",
        "type": "String -> Octicons.Options -> Octicons.Options"
      },
      {
        "name": "comment",
        "comment": "\n",
        "type": "Octicons.Options -> Html.Html msg"
      },
      {
        "name": "commentDiscussion",
        "comment": "\n",
        "type": "Octicons.Options -> Html.Html msg"
      },
      {
        "name": "commentDiscussionPath",
        "comment": "\n",
        "type": "String"
      },
      {
        "name": "commentPath",
        "comment": "\n",
        "type": "String"
      },
      {
        "name": "creditCard",
        "comment": "\n",
        "type": "Octicons.Options -> Html.Html msg"
      },
      {
        "name": "creditCardPath",
        "comment": "\n",
        "type": "String"
      },
      {
        "name": "dash",
        "comment": "\n",
        "type": "Octicons.Options -> Html.Html msg"
      },
      {
        "name": "dashPolygon",
        "comment": "\n",
        "type": "String"
      },
      {
        "name": "dashboard",
        "comment": "\n",
        "type": "Octicons.Options -> Html.Html msg"
      },
      {
        "name": "dashboardPath",
        "comment": "\n",
        "type": "String"
      },
      {
        "name": "database",
        "comment": "\n",
        "type": "Octicons.Options -> Html.Html msg"
      },
      {
        "name": "databasePath",
        "comment": "\n",
        "type": "String"
      },
      {
        "name": "defaultOptions",
        "comment": "\n",
        "type": "Octicons.Options"
      },
      {
        "name": "desktopDownload",
        "comment": "\n",
        "type": "Octicons.Options -> Html.Html msg"
      },
      {
        "name": "desktopDownloadPath",
        "comment": "\n",
        "type": "String"
      },
      {
        "name": "deviceCamera",
        "comment": "\n",
        "type": "Octicons.Options -> Html.Html msg"
      },
      {
        "name": "deviceCameraPath",
        "comment": "\n",
        "type": "String"
      },
      {
        "name": "deviceCameraVideo",
        "comment": "\n",
        "type": "Octicons.Options -> Html.Html msg"
      },
      {
        "name": "deviceCameraVideoPath",
        "comment": "\n",
        "type": "String"
      },
      {
        "name": "deviceDesktop",
        "comment": "\n",
        "type": "Octicons.Options -> Html.Html msg"
      },
      {
        "name": "deviceDesktopPath",
        "comment": "\n",
        "type": "String"
      },
      {
        "name": "deviceMobile",
        "comment": "\n",
        "type": "Octicons.Options -> Html.Html msg"
      },
      {
        "name": "deviceMobilePath",
        "comment": "\n",
        "type": "String"
      },
      {
        "name": "diff",
        "comment": "\n",
        "type": "Octicons.Options -> Html.Html msg"
      },
      {
        "name": "diffAdded",
        "comment": "\n",
        "type": "Octicons.Options -> Html.Html msg"
      },
      {
        "name": "diffAddedPath",
        "comment": "\n",
        "type": "String"
      },
      {
        "name": "diffIgnored",
        "comment": "\n",
        "type": "Octicons.Options -> Html.Html msg"
      },
      {
        "name": "diffIgnoredPath",
        "comment": "\n",
        "type": "String"
      },
      {
        "name": "diffModified",
        "comment": "\n",
        "type": "Octicons.Options -> Html.Html msg"
      },
      {
        "name": "diffModifiedPath",
        "comment": "\n",
        "type": "String"
      },
      {
        "name": "diffPath",
        "comment": "\n",
        "type": "String"
      },
      {
        "name": "diffRemoved",
        "comment": "\n",
        "type": "Octicons.Options -> Html.Html msg"
      },
      {
        "name": "diffRemovedPath",
        "comment": "\n",
        "type": "String"
      },
      {
        "name": "diffRenamed",
        "comment": "\n",
        "type": "Octicons.Options -> Html.Html msg"
      },
      {
        "name": "diffRenamedPath",
        "comment": "\n",
        "type": "String"
      },
      {
        "name": "ellipses",
        "comment": "\n",
        "type": "Octicons.Options -> Html.Html msg"
      },
      {
        "name": "ellipsesPath",
        "comment": "\n",
        "type": "String"
      },
      {
        "name": "ellipsis",
        "comment": "\n",
        "type": "Octicons.Options -> Html.Html msg"
      },
      {
        "name": "ellipsisPath",
        "comment": "\n",
        "type": "String"
      },
      {
        "name": "eye",
        "comment": "\n",
        "type": "Octicons.Options -> Html.Html msg"
      },
      {
        "name": "eyePath",
        "comment": "\n",
        "type": "String"
      },
      {
        "name": "file",
        "comment": "\n",
        "type": "Octicons.Options -> Html.Html msg"
      },
      {
        "name": "fileBinary",
        "comment": "\n",
        "type": "Octicons.Options -> Html.Html msg"
      },
      {
        "name": "fileBinaryPath",
        "comment": "\n",
        "type": "String"
      },
      {
        "name": "fileCode",
        "comment": "\n",
        "type": "Octicons.Options -> Html.Html msg"
      },
      {
        "name": "fileCodePath",
        "comment": "\n",
        "type": "String"
      },
      {
        "name": "fileDirectory",
        "comment": "\n",
        "type": "Octicons.Options -> Html.Html msg"
      },
      {
        "name": "fileDirectoryPath",
        "comment": "\n",
        "type": "String"
      },
      {
        "name": "fileMedia",
        "comment": "\n",
        "type": "Octicons.Options -> Html.Html msg"
      },
      {
        "name": "fileMediaPath",
        "comment": "\n",
        "type": "String"
      },
      {
        "name": "filePath",
        "comment": "\n",
        "type": "String"
      },
      {
        "name": "filePdf",
        "comment": "\n",
        "type": "Octicons.Options -> Html.Html msg"
      },
      {
        "name": "filePdfPath",
        "comment": "\n",
        "type": "String"
      },
      {
        "name": "fileSubmodule",
        "comment": "\n",
        "type": "Octicons.Options -> Html.Html msg"
      },
      {
        "name": "fileSubmodulePath",
        "comment": "\n",
        "type": "String"
      },
      {
        "name": "fileSymlinkDirectory",
        "comment": "\n",
        "type": "Octicons.Options -> Html.Html msg"
      },
      {
        "name": "fileSymlinkDirectoryPath",
        "comment": "\n",
        "type": "String"
      },
      {
        "name": "fileSymlinkFile",
        "comment": "\n",
        "type": "Octicons.Options -> Html.Html msg"
      },
      {
        "name": "fileSymlinkFilePath",
        "comment": "\n",
        "type": "String"
      },
      {
        "name": "fileText",
        "comment": "\n",
        "type": "Octicons.Options -> Html.Html msg"
      },
      {
        "name": "fileTextPath",
        "comment": "\n",
        "type": "String"
      },
      {
        "name": "fileZip",
        "comment": "\n",
        "type": "Octicons.Options -> Html.Html msg"
      },
      {
        "name": "fileZipPath",
        "comment": "\n",
        "type": "String"
      },
      {
        "name": "fillRule",
        "comment": "\n",
        "type": "String -> Octicons.Options -> Octicons.Options"
      },
      {
        "name": "flame",
        "comment": "\n",
        "type": "Octicons.Options -> Html.Html msg"
      },
      {
        "name": "flamePath",
        "comment": "\n",
        "type": "String"
      },
      {
        "name": "fold",
        "comment": "\n",
        "type": "Octicons.Options -> Html.Html msg"
      },
      {
        "name": "foldPath",
        "comment": "\n",
        "type": "String"
      },
      {
        "name": "gear",
        "comment": "\n",
        "type": "Octicons.Options -> Html.Html msg"
      },
      {
        "name": "gearPath",
        "comment": "\n",
        "type": "String"
      },
      {
        "name": "gift",
        "comment": "\n",
        "type": "Octicons.Options -> Html.Html msg"
      },
      {
        "name": "giftPath",
        "comment": "\n",
        "type": "String"
      },
      {
        "name": "gist",
        "comment": "\n",
        "type": "Octicons.Options -> Html.Html msg"
      },
      {
        "name": "gistPath",
        "comment": "\n",
        "type": "String"
      },
      {
        "name": "gistSecret",
        "comment": "\n",
        "type": "Octicons.Options -> Html.Html msg"
      },
      {
        "name": "gistSecretPath",
        "comment": "\n",
        "type": "String"
      },
      {
        "name": "gitBranch",
        "comment": "\n",
        "type": "Octicons.Options -> Html.Html msg"
      },
      {
        "name": "gitBranchPath",
        "comment": "\n",
        "type": "String"
      },
      {
        "name": "gitCommit",
        "comment": "\n",
        "type": "Octicons.Options -> Html.Html msg"
      },
      {
        "name": "gitCommitPath",
        "comment": "\n",
        "type": "String"
      },
      {
        "name": "gitCompare",
        "comment": "\n",
        "type": "Octicons.Options -> Html.Html msg"
      },
      {
        "name": "gitComparePath",
        "comment": "\n",
        "type": "String"
      },
      {
        "name": "gitMerge",
        "comment": "\n",
        "type": "Octicons.Options -> Html.Html msg"
      },
      {
        "name": "gitMergePath",
        "comment": "\n",
        "type": "String"
      },
      {
        "name": "gitPullRequest",
        "comment": "\n",
        "type": "Octicons.Options -> Html.Html msg"
      },
      {
        "name": "gitPullRequestPath",
        "comment": "\n",
        "type": "String"
      },
      {
        "name": "globe",
        "comment": "\n",
        "type": "Octicons.Options -> Html.Html msg"
      },
      {
        "name": "globePath",
        "comment": "\n",
        "type": "String"
      },
      {
        "name": "grabber",
        "comment": "\n",
        "type": "Octicons.Options -> Html.Html msg"
      },
      {
        "name": "grabberPath",
        "comment": "\n",
        "type": "String"
      },
      {
        "name": "graph",
        "comment": "\n",
        "type": "Octicons.Options -> Html.Html msg"
      },
      {
        "name": "graphPath",
        "comment": "\n",
        "type": "String"
      },
      {
        "name": "heart",
        "comment": "\n",
        "type": "Octicons.Options -> Html.Html msg"
      },
      {
        "name": "heartPath",
        "comment": "\n",
        "type": "String"
      },
      {
        "name": "height",
        "comment": "\n",
        "type": "Int -> Octicons.Options -> Octicons.Options"
      },
      {
        "name": "history",
        "comment": "\n",
        "type": "Octicons.Options -> Html.Html msg"
      },
      {
        "name": "historyPath",
        "comment": "\n",
        "type": "String"
      },
      {
        "name": "home",
        "comment": "\n",
        "type": "Octicons.Options -> Html.Html msg"
      },
      {
        "name": "homePath",
        "comment": "\n",
        "type": "String"
      },
      {
        "name": "horizontalRule",
        "comment": "\n",
        "type": "Octicons.Options -> Html.Html msg"
      },
      {
        "name": "horizontalRulePath",
        "comment": "\n",
        "type": "String"
      },
      {
        "name": "hubot",
        "comment": "\n",
        "type": "Octicons.Options -> Html.Html msg"
      },
      {
        "name": "hubotPath",
        "comment": "\n",
        "type": "String"
      },
      {
        "name": "inbox",
        "comment": "\n",
        "type": "Octicons.Options -> Html.Html msg"
      },
      {
        "name": "inboxPath",
        "comment": "\n",
        "type": "String"
      },
      {
        "name": "info",
        "comment": "\n",
        "type": "Octicons.Options -> Html.Html msg"
      },
      {
        "name": "infoPath",
        "comment": "\n",
        "type": "String"
      },
      {
        "name": "issueClosed",
        "comment": "\n",
        "type": "Octicons.Options -> Html.Html msg"
      },
      {
        "name": "issueClosedPath",
        "comment": "\n",
        "type": "String"
      },
      {
        "name": "issueOpened",
        "comment": "\n",
        "type": "Octicons.Options -> Html.Html msg"
      },
      {
        "name": "issueOpenedPath",
        "comment": "\n",
        "type": "String"
      },
      {
        "name": "issueReopened",
        "comment": "\n",
        "type": "Octicons.Options -> Html.Html msg"
      },
      {
        "name": "issueReopenedPath",
        "comment": "\n",
        "type": "String"
      },
      {
        "name": "italic",
        "comment": "\n",
        "type": "Octicons.Options -> Html.Html msg"
      },
      {
        "name": "italicPath",
        "comment": "\n",
        "type": "String"
      },
      {
        "name": "jersey",
        "comment": "\n",
        "type": "Octicons.Options -> Html.Html msg"
      },
      {
        "name": "jerseyPath",
        "comment": "\n",
        "type": "String"
      },
      {
        "name": "key",
        "comment": "\n",
        "type": "Octicons.Options -> Html.Html msg"
      },
      {
        "name": "keyPath",
        "comment": "\n",
        "type": "String"
      },
      {
        "name": "keyboard",
        "comment": "\n",
        "type": "Octicons.Options -> Html.Html msg"
      },
      {
        "name": "keyboardPath",
        "comment": "\n",
        "type": "String"
      },
      {
        "name": "law",
        "comment": "\n",
        "type": "Octicons.Options -> Html.Html msg"
      },
      {
        "name": "lawPath",
        "comment": "\n",
        "type": "String"
      },
      {
        "name": "lightBulb",
        "comment": "\n",
        "type": "Octicons.Options -> Html.Html msg"
      },
      {
        "name": "lightBulbPath",
        "comment": "\n",
        "type": "String"
      },
      {
        "name": "link",
        "comment": "\n",
        "type": "Octicons.Options -> Html.Html msg"
      },
      {
        "name": "linkExternal",
        "comment": "\n",
        "type": "Octicons.Options -> Html.Html msg"
      },
      {
        "name": "linkExternalPath",
        "comment": "\n",
        "type": "String"
      },
      {
        "name": "linkPath",
        "comment": "\n",
        "type": "String"
      },
      {
        "name": "listOrdered",
        "comment": "\n",
        "type": "Octicons.Options -> Html.Html msg"
      },
      {
        "name": "listOrderedPath",
        "comment": "\n",
        "type": "String"
      },
      {
        "name": "listUnordered",
        "comment": "\n",
        "type": "Octicons.Options -> Html.Html msg"
      },
      {
        "name": "listUnorderedPath",
        "comment": "\n",
        "type": "String"
      },
      {
        "name": "location",
        "comment": "\n",
        "type": "Octicons.Options -> Html.Html msg"
      },
      {
        "name": "locationPath",
        "comment": "\n",
        "type": "String"
      },
      {
        "name": "lock",
        "comment": "\n",
        "type": "Octicons.Options -> Html.Html msg"
      },
      {
        "name": "lockPath",
        "comment": "\n",
        "type": "String"
      },
      {
        "name": "logoGist",
        "comment": "\n",
        "type": "Octicons.Options -> Html.Html msg"
      },
      {
        "name": "logoGistPath",
        "comment": "\n",
        "type": "String"
      },
      {
        "name": "logoGithub",
        "comment": "\n",
        "type": "Octicons.Options -> Html.Html msg"
      },
      {
        "name": "logoGithubPath",
        "comment": "\n",
        "type": "String"
      },
      {
        "name": "mail",
        "comment": "\n",
        "type": "Octicons.Options -> Html.Html msg"
      },
      {
        "name": "mailPath",
        "comment": "\n",
        "type": "String"
      },
      {
        "name": "mailRead",
        "comment": "\n",
        "type": "Octicons.Options -> Html.Html msg"
      },
      {
        "name": "mailReadPath",
        "comment": "\n",
        "type": "String"
      },
      {
        "name": "mailReply",
        "comment": "\n",
        "type": "Octicons.Options -> Html.Html msg"
      },
      {
        "name": "mailReplyPath",
        "comment": "\n",
        "type": "String"
      },
      {
        "name": "margin",
        "comment": "\n",
        "type": "String -> Octicons.Options -> Octicons.Options"
      },
      {
        "name": "markGithub",
        "comment": "\n",
        "type": "Octicons.Options -> Html.Html msg"
      },
      {
        "name": "markGithubPath",
        "comment": "\n",
        "type": "String"
      },
      {
        "name": "markTor",
        "comment": "\n",
        "type": "Octicons.Options -> Html.Html msg"
      },
      {
        "name": "markTorPath",
        "comment": "\n",
        "type": "String"
      },
      {
        "name": "markTwitter",
        "comment": "\n",
        "type": "Octicons.Options -> Html.Html msg"
      },
      {
        "name": "markTwitterPath",
        "comment": "\n",
        "type": "String"
      },
      {
        "name": "markdown",
        "comment": "\n",
        "type": "Octicons.Options -> Html.Html msg"
      },
      {
        "name": "markdownPath",
        "comment": "\n",
        "type": "String"
      },
      {
        "name": "megaphone",
        "comment": "\n",
        "type": "Octicons.Options -> Html.Html msg"
      },
      {
        "name": "megaphonePath",
        "comment": "\n",
        "type": "String"
      },
      {
        "name": "mention",
        "comment": "\n",
        "type": "Octicons.Options -> Html.Html msg"
      },
      {
        "name": "mentionPath",
        "comment": "\n",
        "type": "String"
      },
      {
        "name": "milestone",
        "comment": "\n",
        "type": "Octicons.Options -> Html.Html msg"
      },
      {
        "name": "milestonePath",
        "comment": "\n",
        "type": "String"
      },
      {
        "name": "mirror",
        "comment": "\n",
        "type": "Octicons.Options -> Html.Html msg"
      },
      {
        "name": "mirrorPath",
        "comment": "\n",
        "type": "String"
      },
      {
        "name": "mortarBoard",
        "comment": "\n",
        "type": "Octicons.Options -> Html.Html msg"
      },
      {
        "name": "mortarBoardPath",
        "comment": "\n",
        "type": "String"
      },
      {
        "name": "mute",
        "comment": "\n",
        "type": "Octicons.Options -> Html.Html msg"
      },
      {
        "name": "mutePath",
        "comment": "\n",
        "type": "String"
      },
      {
        "name": "noNewline",
        "comment": "\n",
        "type": "Octicons.Options -> Html.Html msg"
      },
      {
        "name": "noNewlinePath",
        "comment": "\n",
        "type": "String"
      },
      {
        "name": "note",
        "comment": "\n",
        "type": "Octicons.Options -> Html.Html msg"
      },
      {
        "name": "notePath",
        "comment": "\n",
        "type": "String"
      },
      {
        "name": "octoface",
        "comment": "\n",
        "type": "Octicons.Options -> Html.Html msg"
      },
      {
        "name": "octofacePath",
        "comment": "\n",
        "type": "String"
      },
      {
        "name": "organization",
        "comment": "\n",
        "type": "Octicons.Options -> Html.Html msg"
      },
      {
        "name": "organizationPath",
        "comment": "\n",
        "type": "String"
      },
      {
        "name": "package",
        "comment": "\n",
        "type": "Octicons.Options -> Html.Html msg"
      },
      {
        "name": "packagePath",
        "comment": "\n",
        "type": "String"
      },
      {
        "name": "paintcan",
        "comment": "\n",
        "type": "Octicons.Options -> Html.Html msg"
      },
      {
        "name": "paintcanPath",
        "comment": "\n",
        "type": "String"
      },
      {
        "name": "pathIconWithOptions",
        "comment": "\n",
        "type": "String -> String -> String -> Octicons.Options -> Html.Html msg"
      },
      {
        "name": "pencil",
        "comment": "\n",
        "type": "Octicons.Options -> Html.Html msg"
      },
      {
        "name": "pencilPath",
        "comment": "\n",
        "type": "String"
      },
      {
        "name": "person",
        "comment": "\n",
        "type": "Octicons.Options -> Html.Html msg"
      },
      {
        "name": "personPath",
        "comment": "\n",
        "type": "String"
      },
      {
        "name": "pin",
        "comment": "\n",
        "type": "Octicons.Options -> Html.Html msg"
      },
      {
        "name": "pinPath",
        "comment": "\n",
        "type": "String"
      },
      {
        "name": "plug",
        "comment": "\n",
        "type": "Octicons.Options -> Html.Html msg"
      },
      {
        "name": "plugPath",
        "comment": "\n",
        "type": "String"
      },
      {
        "name": "plus",
        "comment": "\n",
        "type": "Octicons.Options -> Html.Html msg"
      },
      {
        "name": "plusPolygon",
        "comment": "\n",
        "type": "String"
      },
      {
        "name": "plusSmall",
        "comment": "\n",
        "type": "Octicons.Options -> Html.Html msg"
      },
      {
        "name": "plusSmallPath",
        "comment": "\n",
        "type": "String"
      },
      {
        "name": "polygonIconWithOptions",
        "comment": "\n",
        "type": "String -> String -> String -> Octicons.Options -> Html.Html msg"
      },
      {
        "name": "primitiveDot",
        "comment": "\n",
        "type": "Octicons.Options -> Html.Html msg"
      },
      {
        "name": "primitiveDotPath",
        "comment": "\n",
        "type": "String"
      },
      {
        "name": "primitiveSquare",
        "comment": "\n",
        "type": "Octicons.Options -> Html.Html msg"
      },
      {
        "name": "primitiveSquarePolygon",
        "comment": "\n",
        "type": "String"
      },
      {
        "name": "project",
        "comment": "\n",
        "type": "Octicons.Options -> Html.Html msg"
      },
      {
        "name": "projectPath",
        "comment": "\n",
        "type": "String"
      },
      {
        "name": "pulse",
        "comment": "\n",
        "type": "Octicons.Options -> Html.Html msg"
      },
      {
        "name": "pulsePolygon",
        "comment": "\n",
        "type": "String"
      },
      {
        "name": "question",
        "comment": "\n",
        "type": "Octicons.Options -> Html.Html msg"
      },
      {
        "name": "questionPath",
        "comment": "\n",
        "type": "String"
      },
      {
        "name": "quote",
        "comment": "\n",
        "type": "Octicons.Options -> Html.Html msg"
      },
      {
        "name": "quotePath",
        "comment": "\n",
        "type": "String"
      },
      {
        "name": "radioTower",
        "comment": "\n",
        "type": "Octicons.Options -> Html.Html msg"
      },
      {
        "name": "radioTowerPath",
        "comment": "\n",
        "type": "String"
      },
      {
        "name": "reply",
        "comment": "\n",
        "type": "Octicons.Options -> Html.Html msg"
      },
      {
        "name": "replyPath",
        "comment": "\n",
        "type": "String"
      },
      {
        "name": "repo",
        "comment": "\n",
        "type": "Octicons.Options -> Html.Html msg"
      },
      {
        "name": "repoClone",
        "comment": "\n",
        "type": "Octicons.Options -> Html.Html msg"
      },
      {
        "name": "repoClonePath",
        "comment": "\n",
        "type": "String"
      },
      {
        "name": "repoForcePush",
        "comment": "\n",
        "type": "Octicons.Options -> Html.Html msg"
      },
      {
        "name": "repoForcePushPath",
        "comment": "\n",
        "type": "String"
      },
      {
        "name": "repoForked",
        "comment": "\n",
        "type": "Octicons.Options -> Html.Html msg"
      },
      {
        "name": "repoForkedPath",
        "comment": "\n",
        "type": "String"
      },
      {
        "name": "repoPath",
        "comment": "\n",
        "type": "String"
      },
      {
        "name": "repoPull",
        "comment": "\n",
        "type": "Octicons.Options -> Html.Html msg"
      },
      {
        "name": "repoPullPath",
        "comment": "\n",
        "type": "String"
      },
      {
        "name": "repoPush",
        "comment": "\n",
        "type": "Octicons.Options -> Html.Html msg"
      },
      {
        "name": "repoPushPath",
        "comment": "\n",
        "type": "String"
      },
      {
        "name": "rocket",
        "comment": "\n",
        "type": "Octicons.Options -> Html.Html msg"
      },
      {
        "name": "rocketPath",
        "comment": "\n",
        "type": "String"
      },
      {
        "name": "rss",
        "comment": "\n",
        "type": "Octicons.Options -> Html.Html msg"
      },
      {
        "name": "rssPath",
        "comment": "\n",
        "type": "String"
      },
      {
        "name": "ruby",
        "comment": "\n",
        "type": "Octicons.Options -> Html.Html msg"
      },
      {
        "name": "rubyPath",
        "comment": "\n",
        "type": "String"
      },
      {
        "name": "screenFull",
        "comment": "\n",
        "type": "Octicons.Options -> Html.Html msg"
      },
      {
        "name": "screenFullPath",
        "comment": "\n",
        "type": "String"
      },
      {
        "name": "screenNormal",
        "comment": "\n",
        "type": "Octicons.Options -> Html.Html msg"
      },
      {
        "name": "screenNormalPath",
        "comment": "\n",
        "type": "String"
      },
      {
        "name": "search",
        "comment": "\n",
        "type": "Octicons.Options -> Html.Html msg"
      },
      {
        "name": "searchPath",
        "comment": "\n",
        "type": "String"
      },
      {
        "name": "server",
        "comment": "\n",
        "type": "Octicons.Options -> Html.Html msg"
      },
      {
        "name": "serverPath",
        "comment": "\n",
        "type": "String"
      },
      {
        "name": "settings",
        "comment": "\n",
        "type": "Octicons.Options -> Html.Html msg"
      },
      {
        "name": "settingsPath",
        "comment": "\n",
        "type": "String"
      },
      {
        "name": "shield",
        "comment": "\n",
        "type": "Octicons.Options -> Html.Html msg"
      },
      {
        "name": "shieldPath",
        "comment": "\n",
        "type": "String"
      },
      {
        "name": "signIn",
        "comment": "\n",
        "type": "Octicons.Options -> Html.Html msg"
      },
      {
        "name": "signInPath",
        "comment": "\n",
        "type": "String"
      },
      {
        "name": "signOut",
        "comment": "\n",
        "type": "Octicons.Options -> Html.Html msg"
      },
      {
        "name": "signOutPath",
        "comment": "\n",
        "type": "String"
      },
      {
        "name": "size",
        "comment": "\n",
        "type": "Int -> Octicons.Options -> Octicons.Options"
      },
      {
        "name": "smiley",
        "comment": "\n",
        "type": "Octicons.Options -> Html.Html msg"
      },
      {
        "name": "smileyPath",
        "comment": "\n",
        "type": "String"
      },
      {
        "name": "squirrel",
        "comment": "\n",
        "type": "Octicons.Options -> Html.Html msg"
      },
      {
        "name": "squirrelPath",
        "comment": "\n",
        "type": "String"
      },
      {
        "name": "star",
        "comment": "\n",
        "type": "Octicons.Options -> Html.Html msg"
      },
      {
        "name": "starPolygon",
        "comment": "\n",
        "type": "String"
      },
      {
        "name": "stop",
        "comment": "\n",
        "type": "Octicons.Options -> Html.Html msg"
      },
      {
        "name": "stopPath",
        "comment": "\n",
        "type": "String"
      },
      {
        "name": "style",
        "comment": "\n",
        "type": "String -> Octicons.Options -> Octicons.Options"
      },
      {
        "name": "sync",
        "comment": "\n",
        "type": "Octicons.Options -> Html.Html msg"
      },
      {
        "name": "syncPath",
        "comment": "\n",
        "type": "String"
      },
      {
        "name": "tag",
        "comment": "\n",
        "type": "Octicons.Options -> Html.Html msg"
      },
      {
        "name": "tagPath",
        "comment": "\n",
        "type": "String"
      },
      {
        "name": "tasklist",
        "comment": "\n",
        "type": "Octicons.Options -> Html.Html msg"
      },
      {
        "name": "tasklistPath",
        "comment": "\n",
        "type": "String"
      },
      {
        "name": "telescope",
        "comment": "\n",
        "type": "Octicons.Options -> Html.Html msg"
      },
      {
        "name": "telescopePath",
        "comment": "\n",
        "type": "String"
      },
      {
        "name": "terminal",
        "comment": "\n",
        "type": "Octicons.Options -> Html.Html msg"
      },
      {
        "name": "terminalPath",
        "comment": "\n",
        "type": "String"
      },
      {
        "name": "textSize",
        "comment": "\n",
        "type": "Octicons.Options -> Html.Html msg"
      },
      {
        "name": "textSizePath",
        "comment": "\n",
        "type": "String"
      },
      {
        "name": "threeBars",
        "comment": "\n",
        "type": "Octicons.Options -> Html.Html msg"
      },
      {
        "name": "threeBarsPath",
        "comment": "\n",
        "type": "String"
      },
      {
        "name": "thumbsdown",
        "comment": "\n",
        "type": "Octicons.Options -> Html.Html msg"
      },
      {
        "name": "thumbsdownPath",
        "comment": "\n",
        "type": "String"
      },
      {
        "name": "thumbsup",
        "comment": "\n",
        "type": "Octicons.Options -> Html.Html msg"
      },
      {
        "name": "thumbsupPath",
        "comment": "\n",
        "type": "String"
      },
      {
        "name": "tools",
        "comment": "\n",
        "type": "Octicons.Options -> Html.Html msg"
      },
      {
        "name": "toolsPath",
        "comment": "\n",
        "type": "String"
      },
      {
        "name": "trashcan",
        "comment": "\n",
        "type": "Octicons.Options -> Html.Html msg"
      },
      {
        "name": "trashcanPath",
        "comment": "\n",
        "type": "String"
      },
      {
        "name": "triangleDown",
        "comment": "\n",
        "type": "Octicons.Options -> Html.Html msg"
      },
      {
        "name": "triangleDownPolygon",
        "comment": "\n",
        "type": "String"
      },
      {
        "name": "triangleLeft",
        "comment": "\n",
        "type": "Octicons.Options -> Html.Html msg"
      },
      {
        "name": "triangleLeftPolygon",
        "comment": "\n",
        "type": "String"
      },
      {
        "name": "triangleRight",
        "comment": "\n",
        "type": "Octicons.Options -> Html.Html msg"
      },
      {
        "name": "triangleRightPolygon",
        "comment": "\n",
        "type": "String"
      },
      {
        "name": "triangleUp",
        "comment": "\n",
        "type": "Octicons.Options -> Html.Html msg"
      },
      {
        "name": "triangleUpPolygon",
        "comment": "\n",
        "type": "String"
      },
      {
        "name": "unfold",
        "comment": "\n",
        "type": "Octicons.Options -> Html.Html msg"
      },
      {
        "name": "unfoldPath",
        "comment": "\n",
        "type": "String"
      },
      {
        "name": "unmute",
        "comment": "\n",
        "type": "Octicons.Options -> Html.Html msg"
      },
      {
        "name": "unmutePath",
        "comment": "\n",
        "type": "String"
      },
      {
        "name": "unverified",
        "comment": "\n",
        "type": "Octicons.Options -> Html.Html msg"
      },
      {
        "name": "unverifiedPath",
        "comment": "\n",
        "type": "String"
      },
      {
        "name": "verified",
        "comment": "\n",
        "type": "Octicons.Options -> Html.Html msg"
      },
      {
        "name": "verifiedPath",
        "comment": "\n",
        "type": "String"
      },
      {
        "name": "versions",
        "comment": "\n",
        "type": "Octicons.Options -> Html.Html msg"
      },
      {
        "name": "versionsPath",
        "comment": "\n",
        "type": "String"
      },
      {
        "name": "watch",
        "comment": "\n",
        "type": "Octicons.Options -> Html.Html msg"
      },
      {
        "name": "watchPath",
        "comment": "\n",
        "type": "String"
      },
      {
        "name": "width",
        "comment": "\n",
        "type": "Int -> Octicons.Options -> Octicons.Options"
      },
      {
        "name": "x",
        "comment": "\n",
        "type": "Octicons.Options -> Html.Html msg"
      },
      {
        "name": "xPolygon",
        "comment": "\n",
        "type": "String"
      },
      {
        "name": "zap",
        "comment": "\n",
        "type": "Octicons.Options -> Html.Html msg"
      },
      {
        "name": "zapPolygon",
        "comment": "\n",
        "type": "String"
      }
    ],
    "generated-with-elm-version": "0.18.0"
  }
]